pyionosphere/__init__.py
pyionosphere/d_region.py
pyionosphere-0.0.3b2.dist-info/LICENSE.txt
pyionosphere-0.0.3b2.dist-info/METADATA
pyionosphere-0.0.3b2.dist-info/WHEEL
pyionosphere-0.0.3b2.dist-info/top_level.txt
pyionosphere-0.0.3b2.dist-info/RECORD
